CryptographicFields/__init__.py
CryptographicFields/cryptography.py
CryptographicFields/fields.py
CryptographicFields/filters.py
Django_CryptographicFields-2.1.0.dist-info/LICENSE
Django_CryptographicFields-2.1.0.dist-info/METADATA
Django_CryptographicFields-2.1.0.dist-info/WHEEL
Django_CryptographicFields-2.1.0.dist-info/top_level.txt
Django_CryptographicFields-2.1.0.dist-info/RECORD
