Metadata-Version: 2.1
Name: Django-CryptographicFields
Version: 2.1.0
Summary: A Django app for cryptography in Django Models.
Home-page: https://github.com/Shahprogrammer/Django-CryptographicFields
Author: Shahprogrammer
Author-email: shahprogrammer05@gmail.com
License: UNKNOWN
Platform: UNKNOWN
Classifier: Programming Language :: Python :: 3
Classifier: Programming Language :: Python :: 3.6
Classifier: License :: OSI Approved :: BSD License
Classifier: Operating System :: OS Independent
Classifier: Development Status :: 5 - Production/Stable
Classifier: Framework :: Django :: 3.0
Classifier: Topic :: Security :: Cryptography
Requires-Python: >=3.6
Requires-Dist: django (>=3.0.0)
Requires-Dist: pycryptodome (>=3.9.0)
Requires-Dist: timestring ; python_version<'3.7'
